discoverage
