Metadata-Version: 1.1
Name: django-discoverage
Version: 1.0.0
Summary: Adds coverage to Django's DiscoverRunner.
Home-page: https://github.com/ryankask/django-discoverage
Author: Ryan Kaskel
Author-email: dev@ryankaskel.com
License: BSD
Platform: UNKNOWN
Classifier: Development Status :: 5 - Production/Stable
Classifier: Environment :: Web Environment
Classifier: Framework :: Django
Classifier: Intended Audience :: Developers
Classifier: License :: OSI Approved :: BSD License
Classifier: Operating System :: OS Independent
Classifier: Programming Language :: Python
Classifier: Programming Language :: Python :: 2.6
Classifier: Programming Language :: Python :: 2.7
Classifier: Programming Language :: Python :: 3.2
Classifier: Programming Language :: Python :: 3.3
Classifier: Topic :: Software Development :: Testing
